dify_knowledge_sdk/__init__.py
dify_knowledge_sdk/base_client.py
dify_knowledge_sdk/client.py
dify_knowledge_sdk/exceptions.py
dify_knowledge_sdk/models.py
dify_knowledge_sdk-0.2.0.dist-info/METADATA
dify_knowledge_sdk-0.2.0.dist-info/WHEEL
dify_knowledge_sdk-0.2.0.dist-info/RECORD
