Metadata-Version: 2.4
Name: dify-knowledge-sdk
Version: 0.2.0
Summary: Python SDK for Dify Knowledge Base API
Project-URL: Homepage, https://github.com/LeekJay/dify-knowledge-sdk
Project-URL: Documentation, https://docs.dify.ai/
Project-URL: Repository, https://github.com/LeekJay/dify-knowledge-sdk
Project-URL: Issues, https://github.com/LeekJay/dify-knowledge-sdk/issues
Author: Dify SDK Team
Keywords: api,dify,knowledge-base,sdk
Classifier: Development Status :: 4 - Beta
Classifier: Intended Audience :: Developers
Classifier: License :: OSI Approved :: MIT License
Classifier: Programming Language :: Python :: 3
Classifier: Programming Language :: Python :: 3.8
Classifier: Programming Language :: Python :: 3.9
Classifier: Programming Language :: Python :: 3.10
Classifier: Programming Language :: Python :: 3.11
Classifier: Programming Language :: Python :: 3.12
Classifier: Topic :: Internet :: WWW/HTTP :: Dynamic Content
Classifier: Topic :: Software Development :: Libraries :: Python Modules
Requires-Python: >=3.8.1
Requires-Dist: httpx>=0.28.1
Requires-Dist: pydantic>=2.10.6
Provides-Extra: dev
Requires-Dist: mypy>=1.0.0; extra == 'dev'
Requires-Dist: pytest-asyncio>=0.21.0; extra == 'dev'
Requires-Dist: pytest>=7.0.0; extra == 'dev'
Requires-Dist: ruff>=0.12.7; extra == 'dev'
Provides-Extra: publish
Requires-Dist: build>=1.0.0; extra == 'publish'
Requires-Dist: twine>=6.1.0; extra == 'publish'
